haven/__init__.py
haven/api_client.py
haven/authed_api_client.py
haven/configuration.py
haven/exceptions.py
haven/rest.py
haven/api/__init__.py
haven/api/default_api.py
haven/models/__init__.py
haven/models/account_request_wrapper.py
haven/models/account_sub_type.py
haven/models/account_type.py
haven/models/add_annotation_request.py
haven/models/add_annotation_response.py
haven/models/address.py
haven/models/api_account.py
haven/models/bad_request_service_error.py
haven/models/balance.py
haven/models/bootstrap_strategy.py
haven/models/clean_category.py
haven/models/clean_single_transaction_request.py
haven/models/clean_single_transaction_response.py
haven/models/clean_transaction.py
haven/models/conflict_service_error.py
haven/models/create_webhook_request.py
haven/models/create_webhook_response.py
haven/models/empty_response.py
haven/models/get_accounts_response.py
haven/models/get_merchant_response.py
haven/models/get_transactions_response.py
haven/models/get_webhooks_response.py
haven/models/lat_long.py
haven/models/merchant.py
haven/models/not_found_service_error.py
haven/models/open_hours.py
haven/models/raw_merchant.py
haven/models/raw_merchant_store.py
haven/models/raw_transaction.py
haven/models/service_error.py
haven/models/tenant_service_account_agent_login_request.py
haven/models/tenant_service_account_agent_login_response.py
haven/models/transaction_kind.py
haven/models/transaction_state.py
haven/models/unauthorized_service_error.py
haven/models/uncaught_exception_service_error.py
haven/models/upload_batch_transactions_request.py
haven/models/webhook.py
haven/models/webhook_subscription.py
test/__init__.py
test/test_account_request_wrapper.py
test/test_account_sub_type.py
test/test_account_type.py
test/test_add_annotation_request.py
test/test_add_annotation_response.py
test/test_address.py
test/test_api_account.py
test/test_bad_request_service_error.py
test/test_balance.py
test/test_bootstrap_strategy.py
test/test_clean_category.py
haven_client-0.0.2.dist-info/METADATA
haven_client-0.0.2.dist-info/WHEEL
haven_client-0.0.2.dist-info/top_level.txt
haven_client-0.0.2.dist-info/RECORD
