Metadata-Version: 2.1
Name: haven-client
Version: 0.0.2
Summary: Haven API
Home-page: https://haven.dev
Author-email: emarx@havenmoney.com
License: UNKNOWN
Keywords: Haven API
Platform: UNKNOWN
Classifier: Programming Language :: Python :: 3
Classifier: License :: OSI Approved :: MIT License
Classifier: Operating System :: OS Independent
Requires-Dist: urllib3 (>=1.15)
Requires-Dist: six (>=1.10)
Requires-Dist: certifi
Requires-Dist: python-dateutil
